<annotation>
	<folder>front</folder>
	<filename>1574762532118-Front-01316347676.jpg</filename>
	<path>C:\front\1574762532118-Front-01316347676.jpg</path>
	<source>
		<database>Unknown</database>
	</source>
	<size>
		<width>0</width>
		<height>0</height>
		<depth>3</depth>
	</size>
	<segmented>0</segmented>
	<object>
		<name>old_nid</name>
		<pose>Unspecified</pose>
		<truncated>0</truncated>
		<difficult>0</difficult>
		<bndbox>
			<xmin>145</xmin>
			<ymin>134</ymin>
			<xmax>828</xmax>
			<ymax>562</ymax>
		</bndbox>
	</object>
</annotation>
