<annotation>
	<folder>front</folder>
	<filename>1574794039233-Front-01821278966.jpg</filename>
	<path>C:\front\1574794039233-Front-01821278966.jpg</path>
	<source>
		<database>Unknown</database>
	</source>
	<size>
		<width>0</width>
		<height>0</height>
		<depth>3</depth>
	</size>
	<segmented>0</segmented>
	<object>
		<name>old_nid</name>
		<pose>Unspecified</pose>
		<truncated>0</truncated>
		<difficult>0</difficult>
		<bndbox>
			<xmin>96</xmin>
			<ymin>106</ymin>
			<xmax>803</xmax>
			<ymax>527</ymax>
		</bndbox>
	</object>
</annotation>
