<annotation>
	<folder>front</folder>
	<filename>1575704603130-Front-01910867593.jpg</filename>
	<path>C:\front\1575704603130-Front-01910867593.jpg</path>
	<source>
		<database>Unknown</database>
	</source>
	<size>
		<width>0</width>
		<height>0</height>
		<depth>3</depth>
	</size>
	<segmented>0</segmented>
	<object>
		<name>old_nid</name>
		<pose>Unspecified</pose>
		<truncated>0</truncated>
		<difficult>0</difficult>
		<bndbox>
			<xmin>73</xmin>
			<ymin>100</ymin>
			<xmax>859</xmax>
			<ymax>594</ymax>
		</bndbox>
	</object>
</annotation>
